reminder/__init__.py
reminder/controller.py
reminder/py.typed
reminder/remind.py
reminder/schedule.py
reminder/utils.py
reminder.py-1.0.2.dist-info/LICENSE
reminder.py-1.0.2.dist-info/METADATA
reminder.py-1.0.2.dist-info/WHEEL
reminder.py-1.0.2.dist-info/top_level.txt
reminder.py-1.0.2.dist-info/RECORD
