Metadata-Version: 2.1
Name: reminder.py
Version: 1.0.2
Summary: An async Python schedule reminders with custom event triggers on due time.
Author-email: Snifo <Snifo@mail.com>
License: MIT
Project-URL: Homepage, https://github.com/mrsnifo/reminder.py
Project-URL: Documentation, https://reminderpy.readthedocs.io/latest/
Project-URL: Issue tracker, https://github.com/mrsnifo/reminder.py/issues
Classifier: Development Status :: 5 - Production/Stable
Classifier: License :: OSI Approved :: MIT License
Classifier: Intended Audience :: Developers
Classifier: Natural Language :: English
Classifier: Operating System :: OS Independent
Classifier: Programming Language :: Python :: 3.8
Classifier: Programming Language :: Python :: 3.9
Classifier: Programming Language :: Python :: 3.10
Classifier: Programming Language :: Python :: 3.11
Classifier: Programming Language :: Python :: 3.12
Classifier: Programming Language :: Python :: 3.13
Classifier: Topic :: Software Development :: Libraries
Classifier: Topic :: Software Development :: Libraries :: Python Modules
Classifier: Topic :: Utilities
Classifier: Typing :: Typed
Requires-Python: >=3.8.0
License-File: LICENSE
